pyopp/__init__.py
pyopp/cli.py
pyopp/enums.py
pyopp/highlighter.py
pyopp/main.py
pyopp/utils.py
pyopp-0.0.11.dist-info/METADATA
pyopp-0.0.11.dist-info/WHEEL
pyopp-0.0.11.dist-info/entry_points.txt
pyopp-0.0.11.dist-info/licenses/LICENSE
pyopp-0.0.11.dist-info/RECORD
